libtreelite.so
libtreelite_runtime.so
treelite/__init__.py
treelite/annotator.py
treelite/compat.py
treelite/core.py
treelite/frontend.py
treelite/libpath.py
treelite/common/__init__.py
treelite/common/compat.py
treelite/common/util.py
treelite/contrib/__init__.py
treelite/contrib/gcc.py
treelite/contrib/msvc.py
treelite/contrib/util.py
treelite/gallery/__init__.py
treelite/gallery/sklearn/__init__.py
treelite/gallery/sklearn/common.py
treelite/gallery/sklearn/gbm_classifier.py
treelite/gallery/sklearn/gbm_multi_classifier.py
treelite/gallery/sklearn/gbm_regressor.py
treelite/gallery/sklearn/rf_classifier.py
treelite/gallery/sklearn/rf_multi_classifier.py
treelite/gallery/sklearn/rf_regressor.py
treelite/runtime/__init__.py
treelite/runtime/treelite_runtime/__init__.py
treelite/runtime/treelite_runtime/libpath.py
treelite/runtime/treelite_runtime/predictor.py
treelite/runtime/treelite_runtime/common/__init__.py
treelite/runtime/treelite_runtime/common/compat.py
treelite/runtime/treelite_runtime/common/util.py
treelite_snapshot-0.9.data/data/treelite/VERSION
treelite_snapshot-0.9.data/data/treelite/libtreelite.so
treelite_snapshot-0.9.data/data/treelite/libtreelite_runtime.so
treelite_snapshot-0.9.data/data/treelite/treelite_runtime.zip
treelite_snapshot-0.9.dist-info/METADATA
treelite_snapshot-0.9.dist-info/WHEEL
treelite_snapshot-0.9.dist-info/top_level.txt
treelite_snapshot-0.9.dist-info/RECORD
